{"version":2,"kind":"Notebook","sha256":"c30a767fd355aac7c08e8e4b5bebb1d91f2e01f61ea67c97abe0862f028e5988","slug":"notebooks.intro-to-uxarray.overview","location":"/notebooks/02-intro-to-uxarray/overview.ipynb","dependencies":[],"frontmatter":{"title":"Overview","content_includes_title":true,"kernelspec":{"name":"python3","display_name":"Python 3 (ipykernel)","language":"python"},"authors":[{"nameParsed":{"literal":"The Project Pythia Community","given":"The Project Pythia","family":"Community"},"name":"The Project Pythia Community","id":"contributors-myst-generated-uid-0"}],"open_access":true,"license":{"content":{"id":"CC-BY-4.0","url":"https://creativecommons.org/licenses/by/4.0/","name":"Creative Commons Attribution 4.0 International","free":true,"CC":true},"code":{"id":"Apache-2.0","url":"https://opensource.org/licenses/Apache-2.0","name":"Apache License 2.0","free":true,"osi":true}},"github":"https://github.com/projectpythia/unstructured-grid-viz-cookbook","copyright":"2025","affiliations":[{"id":"University at Albany (State University of New York)","name":"University at Albany (State University of New York)"},{"id":"UCAR/NCAR","name":"UCAR/NCAR"}],"numbering":{"title":{"offset":1}},"edit_url":"https://github.com/projectpythia/unstructured-grid-viz-cookbook/blob/main/notebooks/02-intro-to-uxarray/overview.ipynb","thumbnail":"/unstructured-grid-viz-cookbook/build/e272ded17428f993075a0c5879925b99.svg","exports":[{"format":"ipynb","filename":"overview.ipynb","url":"/unstructured-grid-viz-cookbook/build/overview-b56bd3ceca8b238002f483fdba00f86f.ipynb"}]},"widgets":{},"mdast":{"type":"root","children":[{"type":"block","kind":"notebook-content","children":[{"type":"paragraph","position":{"start":{"line":1,"column":1},"end":{"line":5,"column":1}},"children":[{"type":"image","url":"/unstructured-grid-viz-cookbook/build/e272ded17428f993075a0c5879925b99.svg","alt":"UXarray logo","width":"30%","key":"LB47xgfcLk","urlSource":"https://raw.githubusercontent.com/UXARRAY/uxarray/main/docs/_static/images/logos/uxarray_logo_h_dark.svg"}],"key":"t8QFnQ5xmq"},{"type":"heading","depth":1,"position":{"start":{"line":7,"column":1},"end":{"line":7,"column":1}},"children":[{"type":"text","value":"Overview","position":{"start":{"line":7,"column":1},"end":{"line":7,"column":1}},"key":"q2JQbMogJH"}],"identifier":"overview","label":"Overview","html_id":"overview","implicit":true,"key":"UQEnKsVPXq"},{"type":"heading","depth":3,"position":{"start":{"line":9,"column":1},"end":{"line":9,"column":1}},"children":[{"type":"text","value":"In this section, you’ll learn:","position":{"start":{"line":9,"column":1},"end":{"line":9,"column":1}},"key":"wQIA4MHeNJ"}],"identifier":"in-this-section-youll-learn","label":"In this section, you’ll learn:","html_id":"in-this-section-youll-learn","implicit":true,"key":"W0x3UGU9bH"},{"type":"list","ordered":false,"spread":false,"position":{"start":{"line":11,"column":1},"end":{"line":15,"column":1}},"children":[{"type":"listItem","spread":true,"position":{"start":{"line":11,"column":1},"end":{"line":11,"column":1}},"children":[{"type":"text","value":"What is UXarray?","position":{"start":{"line":11,"column":1},"end":{"line":11,"column":1}},"key":"TDfXpUxyio"}],"key":"vPw6Iis19e"},{"type":"listItem","spread":true,"position":{"start":{"line":12,"column":1},"end":{"line":12,"column":1}},"children":[{"type":"text","value":"Why UXarray?","position":{"start":{"line":12,"column":1},"end":{"line":12,"column":1}},"key":"HpZvP1qYPN"}],"key":"oK8A2mBhXp"},{"type":"listItem","spread":true,"position":{"start":{"line":13,"column":1},"end":{"line":13,"column":1}},"children":[{"type":"text","value":"How UXarray is designed","position":{"start":{"line":13,"column":1},"end":{"line":13,"column":1}},"key":"QZLpBI3VEX"}],"key":"vkoarmKm85"},{"type":"listItem","spread":true,"position":{"start":{"line":14,"column":1},"end":{"line":15,"column":1}},"children":[{"type":"text","value":"UXarray Core API to work with unstructured grids","position":{"start":{"line":14,"column":1},"end":{"line":14,"column":1}},"key":"BvKDkvK9IN"}],"key":"EF4begmtNL"}],"key":"joBD57Txtp"},{"type":"heading","depth":3,"position":{"start":{"line":16,"column":1},"end":{"line":16,"column":1}},"children":[{"type":"text","value":"Related Documentation","position":{"start":{"line":16,"column":1},"end":{"line":16,"column":1}},"key":"B12ey39F4j"}],"identifier":"related-documentation","label":"Related Documentation","html_id":"related-documentation","implicit":true,"key":"mq3cNSxJcd"},{"type":"list","ordered":false,"spread":false,"position":{"start":{"line":18,"column":1},"end":{"line":22,"column":1}},"children":[{"type":"listItem","spread":true,"position":{"start":{"line":18,"column":1},"end":{"line":18,"column":1}},"children":[{"type":"link","url":"https://uxarray.readthedocs.io/en/latest/index.html","position":{"start":{"line":18,"column":1},"end":{"line":18,"column":1}},"children":[{"type":"text","value":"UXarray Homepage","position":{"start":{"line":18,"column":1},"end":{"line":18,"column":1}},"key":"yYdGJaKLmH"}],"urlSource":"https://uxarray.readthedocs.io/en/latest/index.html","key":"AnFDLw0dvt"}],"key":"Un6qxNnUYv"},{"type":"listItem","spread":true,"position":{"start":{"line":19,"column":1},"end":{"line":19,"column":1}},"children":[{"type":"link","url":"https://uxarray.readthedocs.io/en/latest/getting-started/overview.html","position":{"start":{"line":19,"column":1},"end":{"line":19,"column":1}},"children":[{"type":"text","value":"UXarray “Why UXarray?” Documentation","position":{"start":{"line":19,"column":1},"end":{"line":19,"column":1}},"key":"fcdAdNLIzW"}],"urlSource":"https://uxarray.readthedocs.io/en/latest/getting-started/overview.html","key":"JQKf11RdmW"}],"key":"kfdP3YDTFH"},{"type":"listItem","spread":true,"position":{"start":{"line":20,"column":1},"end":{"line":20,"column":1}},"children":[{"type":"link","url":"https://uxarray.readthedocs.io/en/latest/user-guide/data-structures.html","position":{"start":{"line":20,"column":1},"end":{"line":20,"column":1}},"children":[{"type":"text","value":"UXarray Data Structures Documentation","position":{"start":{"line":20,"column":1},"end":{"line":20,"column":1}},"key":"PW9hxcV6l9"}],"urlSource":"https://uxarray.readthedocs.io/en/latest/user-guide/data-structures.html","key":"nrtkbS1dyT"}],"key":"Tr3N1rXska"},{"type":"listItem","spread":true,"position":{"start":{"line":21,"column":1},"end":{"line":22,"column":1}},"children":[{"type":"link","url":"https://uxarray.readthedocs.io/en/latest/user-guide/grid-formats.html","position":{"start":{"line":21,"column":1},"end":{"line":21,"column":1}},"children":[{"type":"text","value":"UXarray Supported Models & Grid Formats Documentation","position":{"start":{"line":21,"column":1},"end":{"line":21,"column":1}},"key":"TXeP38TCCa"}],"urlSource":"https://uxarray.readthedocs.io/en/latest/user-guide/grid-formats.html","key":"G0v6QdpjOc"}],"key":"G9CLVOYHKC"}],"key":"gG1U4YOrrY"},{"type":"heading","depth":3,"position":{"start":{"line":23,"column":1},"end":{"line":23,"column":1}},"children":[{"type":"text","value":"Prerequisites","position":{"start":{"line":23,"column":1},"end":{"line":23,"column":1}},"key":"wKbr0Rmatd"}],"identifier":"prerequisites","label":"Prerequisites","html_id":"prerequisites","implicit":true,"key":"wP0XQh4vyr"},{"type":"table","position":{"start":{"line":25,"column":1},"end":{"line":27,"column":1}},"children":[{"type":"tableRow","position":{"start":{"line":25,"column":1},"end":{"line":25,"column":1}},"children":[{"type":"tableCell","header":true,"position":{"start":{"line":25,"column":1},"end":{"line":25,"column":1}},"children":[{"type":"text","value":"Concepts","position":{"start":{"line":25,"column":1},"end":{"line":25,"column":1}},"key":"gj9xb5tLwN"}],"key":"k2GwvH1KTG"},{"type":"tableCell","header":true,"position":{"start":{"line":25,"column":1},"end":{"line":25,"column":1}},"children":[{"type":"text","value":"Importance","position":{"start":{"line":25,"column":1},"end":{"line":25,"column":1}},"key":"mEKwgayXPa"}],"key":"pWWDDmqJSq"},{"type":"tableCell","header":true,"position":{"start":{"line":25,"column":1},"end":{"line":25,"column":1}},"children":[{"type":"text","value":"Notes","position":{"start":{"line":25,"column":1},"end":{"line":25,"column":1}},"key":"l6BIaxWOZp"}],"key":"BcU5k2wYvX"}],"key":"SSbqAhswuQ"},{"type":"tableRow","position":{"start":{"line":27,"column":1},"end":{"line":27,"column":1}},"children":[{"type":"tableCell","position":{"start":{"line":27,"column":1},"end":{"line":27,"column":1}},"children":[{"type":"link","url":"https://docs.xarray.dev/en/stable/","position":{"start":{"line":27,"column":1},"end":{"line":27,"column":1}},"children":[{"type":"text","value":"Xarray","position":{"start":{"line":27,"column":1},"end":{"line":27,"column":1}},"key":"Uepx4oyy6d"}],"urlSource":"https://docs.xarray.dev/en/stable/","key":"DjfiqQKBw3"}],"key":"t4aJHvumjP"},{"type":"tableCell","position":{"start":{"line":27,"column":1},"end":{"line":27,"column":1}},"children":[{"type":"text","value":"Necessary","position":{"start":{"line":27,"column":1},"end":{"line":27,"column":1}},"key":"tKE0yi8R46"}],"key":"i1mdm5L5xm"},{"type":"tableCell","position":{"start":{"line":27,"column":1},"end":{"line":27,"column":1}},"children":[],"key":"n4laLhqMOm"}],"key":"XXPaHytNLe"}],"key":"dsYRyosffX"},{"type":"paragraph","position":{"start":{"line":29,"column":1},"end":{"line":29,"column":1}},"children":[{"type":"strong","position":{"start":{"line":29,"column":1},"end":{"line":29,"column":1}},"children":[{"type":"text","value":"Time to learn","position":{"start":{"line":29,"column":1},"end":{"line":29,"column":1}},"key":"tB7eprgyzd"}],"key":"cwKzmAVPDL"},{"type":"text","value":": 10 minutes","position":{"start":{"line":29,"column":1},"end":{"line":29,"column":1}},"key":"nhFut9KZET"}],"key":"dgei75k6i3"},{"type":"thematicBreak","position":{"start":{"line":31,"column":1},"end":{"line":31,"column":1}},"key":"WozaPFFcWV"}],"key":"RjjNRcPx5u"},{"type":"block","kind":"notebook-content","children":[{"type":"heading","depth":2,"position":{"start":{"line":1,"column":1},"end":{"line":1,"column":1}},"children":[{"type":"text","value":"What is UXarray?","position":{"start":{"line":1,"column":1},"end":{"line":1,"column":1}},"key":"AqCVYP9hkO"}],"identifier":"what-is-uxarray","label":"What is UXarray?","html_id":"what-is-uxarray","implicit":true,"key":"mPfs7HpCKq"}],"key":"HJFCuOMpYM"},{"type":"block","kind":"notebook-content","children":[{"type":"paragraph","position":{"start":{"line":1,"column":1},"end":{"line":1,"column":1}},"children":[{"type":"text","value":"The “U” in UXarray stands for “Unstructured Grids”. UXarray extends upon and inherits from ","position":{"start":{"line":1,"column":1},"end":{"line":1,"column":1}},"key":"ppexb0fhh2"},{"type":"link","url":"https://docs.xarray.dev/en/stable/","position":{"start":{"line":1,"column":1},"end":{"line":1,"column":1}},"children":[{"type":"text","value":"Xarray","position":{"start":{"line":1,"column":1},"end":{"line":1,"column":1}},"key":"WUmCOVcz7f"}],"urlSource":"https://docs.xarray.dev/en/stable/","key":"ih3KgnNUUj"},{"type":"text","value":" for providing the Earth system sciences community with analysis and visualization functionality that can operate directly on the native unstructured mesh data resulting from climate and global weather models and observations.","position":{"start":{"line":1,"column":1},"end":{"line":1,"column":1}},"key":"jD88FFmJwR"}],"key":"UJWIicFsyB"},{"type":"paragraph","position":{"start":{"line":3,"column":1},"end":{"line":3,"column":1}},"children":[{"type":"text","value":"UXarray is written around the ","position":{"start":{"line":3,"column":1},"end":{"line":3,"column":1}},"key":"FBoObt6IJk"},{"type":"link","url":"http://ugrid-conventions.github.io/ugrid-conventions/","position":{"start":{"line":3,"column":1},"end":{"line":3,"column":1}},"children":[{"type":"text","value":"UGRID","position":{"start":{"line":3,"column":1},"end":{"line":3,"column":1}},"key":"UvJuZPjOTE"}],"urlSource":"http://ugrid-conventions.github.io/ugrid-conventions/","key":"XM51hgTnkd"},{"type":"text","value":" conventions to represent several different unstructured mesh types in an unified, ","position":{"start":{"line":3,"column":1},"end":{"line":3,"column":1}},"key":"Q6k8fPYsQ3"},{"type":"link","url":"http://cfconventions.org/","position":{"start":{"line":3,"column":1},"end":{"line":3,"column":1}},"children":[{"type":"text","value":"Climate and Forecast metadata convention (CF)","position":{"start":{"line":3,"column":1},"end":{"line":3,"column":1}},"key":"YIpS6DNDyp"}],"urlSource":"http://cfconventions.org/","key":"LDrk2eljiO"},{"type":"text","value":"-compliant format.","position":{"start":{"line":3,"column":1},"end":{"line":3,"column":1}},"key":"r44KBhfKzK"}],"key":"VrIS9XDXDu"},{"type":"paragraph","position":{"start":{"line":5,"column":1},"end":{"line":5,"column":1}},"children":[{"type":"text","value":"Specifically, UXarray’s core functionality supports horizontally unstructured grids with vertical levels as defined by the 2D Flexible Mesh Topology in the UGRID conventions, which can contain a mix of triangles, quadrilaterals, or other geometric faces.","position":{"start":{"line":5,"column":1},"end":{"line":5,"column":1}},"key":"hr0U78ox0O"}],"key":"ZlbRybHndH"}],"key":"RBUOQP5JnT"},{"type":"block","kind":"notebook-content","children":[{"type":"heading","depth":2,"position":{"start":{"line":1,"column":1},"end":{"line":1,"column":1}},"children":[{"type":"text","value":"Why UXarray?","position":{"start":{"line":1,"column":1},"end":{"line":1,"column":1}},"key":"rWOvf4iBwB"}],"identifier":"why-uxarray","label":"Why UXarray?","html_id":"why-uxarray","implicit":true,"key":"UPnMUVObjp"}],"key":"fLGvOTWSXI"},{"type":"block","kind":"notebook-content","children":[{"type":"paragraph","position":{"start":{"line":1,"column":1},"end":{"line":1,"column":1}},"children":[{"type":"text","value":"UXarray can simplify working with unstructured grids because it:","position":{"start":{"line":1,"column":1},"end":{"line":1,"column":1}},"key":"ZrkvvljnpT"}],"key":"JtZaySb6T9"},{"type":"list","ordered":false,"spread":false,"position":{"start":{"line":3,"column":1},"end":{"line":15,"column":1}},"children":[{"type":"listItem","spread":true,"position":{"start":{"line":3,"column":1},"end":{"line":4,"column":1}},"children":[{"type":"paragraph","position":{"start":{"line":3,"column":1},"end":{"line":3,"column":1}},"children":[{"type":"text","value":"Enables significant data analysis and visualization functionality to be executed directly on unstructured grids","position":{"start":{"line":3,"column":1},"end":{"line":3,"column":1}},"key":"BYDPZfXLnr"}],"key":"WwZxYO4GoP"}],"key":"lMcjcSoqsF"},{"type":"listItem","spread":true,"position":{"start":{"line":5,"column":1},"end":{"line":6,"column":1}},"children":[{"type":"paragraph","position":{"start":{"line":5,"column":1},"end":{"line":5,"column":1}},"children":[{"type":"text","value":"Adheres to the UGRID specifications for compatibility across a variety of mesh formats","position":{"start":{"line":5,"column":1},"end":{"line":5,"column":1}},"key":"bK2MrIjOCa"}],"key":"hwMvL4ivwe"}],"key":"MumAo1hz8C"},{"type":"listItem","spread":true,"position":{"start":{"line":7,"column":1},"end":{"line":8,"column":1}},"children":[{"type":"paragraph","position":{"start":{"line":7,"column":1},"end":{"line":7,"column":1}},"children":[{"type":"text","value":"Provides a single interface for supporting a variety of unstructured grid formats including UGRID, MPAS, SCRIP, and Exodus (See the full list of ","position":{"start":{"line":7,"column":1},"end":{"line":7,"column":1}},"key":"O3HiKz62HN"},{"type":"link","url":"https://uxarray.readthedocs.io/en/latest/user-guide/grid-formats.html","position":{"start":{"line":7,"column":1},"end":{"line":7,"column":1}},"children":[{"type":"text","value":"UXarray’s supported models and grid formats","position":{"start":{"line":7,"column":1},"end":{"line":7,"column":1}},"key":"K69ROKfVRd"}],"urlSource":"https://uxarray.readthedocs.io/en/latest/user-guide/grid-formats.html","key":"Wh1iilVJFO"},{"type":"text","value":")","position":{"start":{"line":7,"column":1},"end":{"line":7,"column":1}},"key":"UQyEH8mA13"}],"key":"tTLvPmL52E"}],"key":"sbBIQmNmEA"},{"type":"listItem","spread":true,"position":{"start":{"line":9,"column":1},"end":{"line":10,"column":1}},"children":[{"type":"paragraph","position":{"start":{"line":9,"column":1},"end":{"line":9,"column":1}},"children":[{"type":"text","value":"Inherits from Xarray, providing simplified data using familiar (Xarray-like) data structures and operations","position":{"start":{"line":9,"column":1},"end":{"line":9,"column":1}},"key":"FSmYvbgwsi"}],"key":"a8mVNIkpIK"}],"key":"j4wMbe0iOh"},{"type":"listItem","spread":true,"position":{"start":{"line":11,"column":1},"end":{"line":12,"column":1}},"children":[{"type":"paragraph","position":{"start":{"line":11,"column":1},"end":{"line":11,"column":1}},"children":[{"type":"text","value":"Brings standardization to unstructured mesh support for climate data analysis and visualization","position":{"start":{"line":11,"column":1},"end":{"line":11,"column":1}},"key":"xyDgoNdYHo"}],"key":"uHhyA5oDWO"}],"key":"kIaMDO69ib"},{"type":"listItem","spread":true,"position":{"start":{"line":13,"column":1},"end":{"line":14,"column":1}},"children":[{"type":"paragraph","position":{"start":{"line":13,"column":1},"end":{"line":13,"column":1}},"children":[{"type":"text","value":"Builds on optimized data structures and algorithms for handling large and complex unstructured datasets","position":{"start":{"line":13,"column":1},"end":{"line":13,"column":1}},"key":"CU2ORjjaJ8"}],"key":"AyLFtePwoz"}],"key":"ewA29fn30E"},{"type":"listItem","spread":true,"position":{"start":{"line":15,"column":1},"end":{"line":15,"column":1}},"children":[{"type":"paragraph","position":{"start":{"line":15,"column":1},"end":{"line":15,"column":1}},"children":[{"type":"text","value":"Supports enhanced interoperability and community collaboration","position":{"start":{"line":15,"column":1},"end":{"line":15,"column":1}},"key":"S3Xrwk7SbS"}],"key":"NAwOn3QaVM"}],"key":"XbPnoUH14x"}],"key":"R2lcYLPCkj"}],"key":"FKivricRbO"},{"type":"block","kind":"notebook-content","children":[{"type":"heading","depth":2,"position":{"start":{"line":1,"column":1},"end":{"line":1,"column":1}},"children":[{"type":"text","value":"UXarray Design","position":{"start":{"line":1,"column":1},"end":{"line":1,"column":1}},"key":"gFKRyFOec0"}],"identifier":"uxarray-design","label":"UXarray Design","html_id":"uxarray-design","implicit":true,"key":"C0ds0mhW29"}],"key":"vYS5W5Xn2r"},{"type":"block","kind":"notebook-content","children":[{"type":"paragraph","position":{"start":{"line":1,"column":1},"end":{"line":1,"column":1}},"children":[{"type":"text","value":"UXarray is designed around three core data structures, ","position":{"start":{"line":1,"column":1},"end":{"line":1,"column":1}},"key":"sJD7xOkk3O"},{"type":"inlineCode","value":"Grid","position":{"start":{"line":1,"column":1},"end":{"line":1,"column":1}},"key":"p3dwbW4DpN"},{"type":"text","value":", ","position":{"start":{"line":1,"column":1},"end":{"line":1,"column":1}},"key":"RVS5vJFrpL"},{"type":"inlineCode","value":"UxDataset","position":{"start":{"line":1,"column":1},"end":{"line":1,"column":1}},"key":"duUnvNPo8Y"},{"type":"text","value":", and ","position":{"start":{"line":1,"column":1},"end":{"line":1,"column":1}},"key":"Hu6awgUMes"},{"type":"inlineCode","value":"UxDataArray","position":{"start":{"line":1,"column":1},"end":{"line":1,"column":1}},"key":"TTQwLM6vBd"},{"type":"text","value":":","position":{"start":{"line":1,"column":1},"end":{"line":1,"column":1}},"key":"XavLFbfN5W"}],"key":"AyN1vh9BhQ"},{"type":"list","ordered":false,"spread":false,"position":{"start":{"line":3,"column":1},"end":{"line":7,"column":1}},"children":[{"type":"listItem","spread":true,"position":{"start":{"line":3,"column":1},"end":{"line":4,"column":1}},"children":[{"type":"paragraph","position":{"start":{"line":3,"column":1},"end":{"line":3,"column":1}},"children":[{"type":"inlineCode","value":"Grid","position":{"start":{"line":3,"column":1},"end":{"line":3,"column":1}},"key":"W5egLv5ysK"},{"type":"text","value":" provides unstructured grid awareness for the data analysis and visualization functionality implemented through ","position":{"start":{"line":3,"column":1},"end":{"line":3,"column":1}},"key":"GyLekgkABw"},{"type":"inlineCode","value":"UxDataset","position":{"start":{"line":3,"column":1},"end":{"line":3,"column":1}},"key":"CGqvVJPea5"},{"type":"text","value":" and ","position":{"start":{"line":3,"column":1},"end":{"line":3,"column":1}},"key":"soZnEDJ50s"},{"type":"inlineCode","value":"UxDataArray","position":{"start":{"line":3,"column":1},"end":{"line":3,"column":1}},"key":"vAKVycyo1M"},{"type":"text","value":". It houses grid-specific methods and topology variables.","position":{"start":{"line":3,"column":1},"end":{"line":3,"column":1}},"key":"nrrzz9FozN"}],"key":"KRn6pAdve6"}],"key":"pMhnSnOvUw"},{"type":"listItem","spread":true,"position":{"start":{"line":5,"column":1},"end":{"line":6,"column":1}},"children":[{"type":"paragraph","position":{"start":{"line":5,"column":1},"end":{"line":5,"column":1}},"children":[{"type":"inlineCode","value":"UxDataset","position":{"start":{"line":5,"column":1},"end":{"line":5,"column":1}},"key":"aqFiU7Xgor"},{"type":"text","value":" inherits from the ","position":{"start":{"line":5,"column":1},"end":{"line":5,"column":1}},"key":"eQkTZjHIaA"},{"type":"inlineCode","value":"xarray.Dataset","position":{"start":{"line":5,"column":1},"end":{"line":5,"column":1}},"key":"SDjIBHaTfL"},{"type":"text","value":" class, providing much of the same functionality but extended to operate on Unstructured Grids through new and overloaded methods. Each ","position":{"start":{"line":5,"column":1},"end":{"line":5,"column":1}},"key":"N9s5Ybsxhn"},{"type":"inlineCode","value":"UxDataset","position":{"start":{"line":5,"column":1},"end":{"line":5,"column":1}},"key":"f9H9jAlS9g"},{"type":"text","value":" is linked to its own ","position":{"start":{"line":5,"column":1},"end":{"line":5,"column":1}},"key":"DfOf20kBNq"},{"type":"inlineCode","value":"Grid","position":{"start":{"line":5,"column":1},"end":{"line":5,"column":1}},"key":"GHbt1FXQUq"},{"type":"text","value":" object through the use of a class property (","position":{"start":{"line":5,"column":1},"end":{"line":5,"column":1}},"key":"xv47Cffbol"},{"type":"inlineCode","value":"UxDataset.uxgrid","position":{"start":{"line":5,"column":1},"end":{"line":5,"column":1}},"key":"ur3TFJB5rq"},{"type":"text","value":") to provide a grid-aware implementation. An instance of ","position":{"start":{"line":5,"column":1},"end":{"line":5,"column":1}},"key":"J9oVb42BZf"},{"type":"inlineCode","value":"UxDataset","position":{"start":{"line":5,"column":1},"end":{"line":5,"column":1}},"key":"gGNFeM271n"},{"type":"text","value":" can be thought of as a collection of data variables, i.e. ","position":{"start":{"line":5,"column":1},"end":{"line":5,"column":1}},"key":"Umc57tfFGo"},{"type":"inlineCode","value":"UxDataArray","position":{"start":{"line":5,"column":1},"end":{"line":5,"column":1}},"key":"ikW8e6sGrp"},{"type":"text","value":" objects, that reside on a particular Unstructured Grid as defined in the ","position":{"start":{"line":5,"column":1},"end":{"line":5,"column":1}},"key":"sfF2vjTINu"},{"type":"inlineCode","value":"uxgrid","position":{"start":{"line":5,"column":1},"end":{"line":5,"column":1}},"key":"gvq9gVDTAN"},{"type":"text","value":" property.","position":{"start":{"line":5,"column":1},"end":{"line":5,"column":1}},"key":"LuVLutw24p"}],"key":"kCzh7KUiQd"}],"key":"LCKOdm7bny"},{"type":"listItem","spread":true,"position":{"start":{"line":7,"column":1},"end":{"line":7,"column":1}},"children":[{"type":"paragraph","position":{"start":{"line":7,"column":1},"end":{"line":7,"column":1}},"children":[{"type":"inlineCode","value":"UxDataArray","position":{"start":{"line":7,"column":1},"end":{"line":7,"column":1}},"key":"eWFmnjgdZe"},{"type":"text","value":" similarly inherits from the ","position":{"start":{"line":7,"column":1},"end":{"line":7,"column":1}},"key":"wFsfhAPhz2"},{"type":"inlineCode","value":"xarray.DataArray","position":{"start":{"line":7,"column":1},"end":{"line":7,"column":1}},"key":"kCAqc0FQRy"},{"type":"text","value":" class, providing single data variable-level functionality to operate on Unstructured Grids through new and overloaded methods. Similar to ","position":{"start":{"line":7,"column":1},"end":{"line":7,"column":1}},"key":"I7syhPitH0"},{"type":"inlineCode","value":"UxDataset","position":{"start":{"line":7,"column":1},"end":{"line":7,"column":1}},"key":"OeKwHHev53"},{"type":"text","value":", it has a link to its own ","position":{"start":{"line":7,"column":1},"end":{"line":7,"column":1}},"key":"lPdgWn3Gbe"},{"type":"inlineCode","value":"Grid","position":{"start":{"line":7,"column":1},"end":{"line":7,"column":1}},"key":"JWT1WVoaMf"},{"type":"text","value":" object (","position":{"start":{"line":7,"column":1},"end":{"line":7,"column":1}},"key":"balMzqClCy"},{"type":"inlineCode","value":"UxDataArray.uxgrid","position":{"start":{"line":7,"column":1},"end":{"line":7,"column":1}},"key":"gmhwgYV2r0"},{"type":"text","value":"). For isntance, if several ","position":{"start":{"line":7,"column":1},"end":{"line":7,"column":1}},"key":"Bmg6YJNHLJ"},{"type":"inlineCode","value":"UxDataArray","position":{"start":{"line":7,"column":1},"end":{"line":7,"column":1}},"key":"kqHxQyImr4"},{"type":"text","value":" variables exist in an ","position":{"start":{"line":7,"column":1},"end":{"line":7,"column":1}},"key":"kJCvxrVeJh"},{"type":"inlineCode","value":"UxDataset","position":{"start":{"line":7,"column":1},"end":{"line":7,"column":1}},"key":"BJgnc1jG1I"},{"type":"text","value":" object, each of them will have a link to the same ","position":{"start":{"line":7,"column":1},"end":{"line":7,"column":1}},"key":"cmNyAYOcwf"},{"type":"inlineCode","value":"Grid","position":{"start":{"line":7,"column":1},"end":{"line":7,"column":1}},"key":"WltQos8pLk"},{"type":"text","value":" object that proves all of them reside on the same unstructured grid topology.","position":{"start":{"line":7,"column":1},"end":{"line":7,"column":1}},"key":"VaRWkuUCJJ"}],"key":"BF5eTuY3F4"}],"key":"eKPQ9EMnHb"}],"key":"Oy8SIwPo47"}],"key":"dmSbvjRcpb"},{"type":"block","kind":"notebook-content","children":[{"type":"div","class":"admonition alert alert-info","children":[{"type":"paragraph","children":[{"type":"text","value":"Note:","key":"mzs2Q8nunn"}],"key":"tUBVMalw0b"},{"type":"text","value":"The following notebooks will detail each of these data structures; hence, we are keeping it short here in this section.","key":"gogYosrXzb"}],"key":"pqgJKJxzXU"}],"key":"GhKRbKUoMI"},{"type":"block","kind":"notebook-content","children":[{"type":"paragraph","position":{"start":{"line":1,"column":1},"end":{"line":1,"column":1}},"children":[{"type":"text","value":"Given the introductions to the core UXarray data structures, let us have a look at the UXarray design diagram below:","position":{"start":{"line":1,"column":1},"end":{"line":1,"column":1}},"key":"O7llaN3X7q"}],"key":"gHZauLazPm"}],"key":"oLbSLWyrPQ"},{"type":"block","kind":"notebook-content","children":[{"type":"image","url":"/unstructured-grid-viz-cookbook/build/uxarray-design-12424763df25c7a04cfcee4067b18b69.png","title":"UXarray Design","alt":"Grid UxDataset and UxDataArray","width":1200,"key":"sp6y4KgRtX","urlSource":"../../_static/images/uxarray-design.png"}],"key":"FvuzgJbN32"},{"type":"block","kind":"notebook-content","children":[{"type":"heading","depth":2,"position":{"start":{"line":1,"column":1},"end":{"line":1,"column":1}},"children":[{"type":"text","value":"UXarray’s Core API and Unstructured Grids","position":{"start":{"line":1,"column":1},"end":{"line":1,"column":1}},"key":"NULRt6nMtM"}],"identifier":"uxarrays-core-api-and-unstructured-grids","label":"UXarray’s Core API and Unstructured Grids","html_id":"uxarrays-core-api-and-unstructured-grids","implicit":true,"key":"ophR9MA0SH"}],"key":"wlKUk0iBcy"},{"type":"block","kind":"notebook-content","children":[{"type":"paragraph","position":{"start":{"line":1,"column":1},"end":{"line":1,"column":1}},"children":[{"type":"text","value":"When working with unstructured grids, the grid topology definition is typically stored in a dedicated grid file, separately from any data file(s), i.e. the whole dataset contains a single grid definition file along with one or more data files. However, in other less common cases, the grid definition might be embedded into the data file(s).","position":{"start":{"line":1,"column":1},"end":{"line":1,"column":1}},"key":"i5pe8PzCWh"}],"key":"p9LgLqEzw4"},{"type":"paragraph","position":{"start":{"line":3,"column":1},"end":{"line":3,"column":1}},"children":[{"type":"text","value":"UXarray is able to handle both of these cases thanks to the core API for opening grid and data files (or other storage objects). The following notebooks in this chapter will cover the core API for these cases.","position":{"start":{"line":3,"column":1},"end":{"line":3,"column":1}},"key":"fbpKMJrkui"}],"key":"SIgWG8zGoj"}],"key":"TxLTnfLIPx"},{"type":"block","kind":"notebook-content","children":[{"type":"heading","depth":2,"position":{"start":{"line":1,"column":1},"end":{"line":1,"column":1}},"children":[{"type":"text","value":"What is next?","position":{"start":{"line":1,"column":1},"end":{"line":1,"column":1}},"key":"Aoa3scLfOz"}],"identifier":"what-is-next","label":"What is next?","html_id":"what-is-next","implicit":true,"key":"shh6KJImMa"},{"type":"paragraph","position":{"start":{"line":2,"column":1},"end":{"line":2,"column":1}},"children":[{"type":"text","value":"The next section will provide an introduction to the UXarray’s ","position":{"start":{"line":2,"column":1},"end":{"line":2,"column":1}},"key":"DukwGna6zI"},{"type":"inlineCode","value":"Grid","position":{"start":{"line":2,"column":1},"end":{"line":2,"column":1}},"key":"U6R3mYwuI8"},{"type":"text","value":" class and how to open standalone grid files.","position":{"start":{"line":2,"column":1},"end":{"line":2,"column":1}},"key":"rB4K2gfHyo"}],"key":"L4NxjQjn1c"}],"key":"uT1ptt0Rra"}],"key":"jRPLXix4c7"},"references":{"cite":{"order":[],"data":{}}},"footer":{"navigation":{"prev":{"title":"Rendering Techniques","url":"/notebooks/foundations/rendering-techniques","group":"Foundations"},"next":{"title":"UXarray Grid","url":"/notebooks/intro-to-uxarray/grid","group":"Introduction to UXarray"}}},"domain":"http://localhost:3000"}